<?xml version="1.0" encoding="utf-8"?>
<?xml-stylesheet type="text/xsl" href="GatoXSL.xsl"?> 
<gato xmlns:xsi="http://www.w3.org/2001/XMLSchema-instance" xsi:noNamespaceSchemaLocation="Gato.xsd">
	<titulo>Fabricar refugio gatos callejeros DIY</titulo>
	<tema>MATERIALES</tema>
	<autor>Mónica y Mar</autor>
	<main>
		<norma>
			<linea>CAJA DE CARTóN</linea>	
			<linea>Estructura básica.</linea>
			<linea>Elegir un buen tamaño, no muy grande ni muy pequeña.</linea>
		</norma>
		<norma>
			<linea>TETABRIKS</linea>		
			 <linea>Estructura impermeable, pegada a la caja.</linea>	
		</norma>
	    <norma>
			<linea>TIJERAS</linea>		
			 <linea>Para abrir los tetabriks.</linea>	
		</norma>
		<norma>
			<linea>CINTA ESTILO AMERICANA</linea>		
			 <linea>Asegurar bordes.</linea>	
		</norma>
	</main>
</gato>