<?xml version="1.0" encoding="utf-8"?>
<?xml-stylesheet type="text/xsl" href="GatoXSL.xsl"?> 
<gato xmlns:xsi="http://www.w3.org/2001/XMLSchema-instance" xsi:noNamespaceSchemaLocation="pasos.xsd">
	<titulo>¿Cómo hacer la casa?</titulo>
	<tema>PASOS</tema>
	<autor>Mónica y Mar</autor>
	<main>
	   <norma>
			<linea>1. Cortar los tetrabriks, y así abrilos completamente.</linea>		
			<linea>2. Colocar los tetrabriks abiertos alrededor y pegados a la caja.</linea>		
			<linea>3. Pegar con cinta el tabrik a la caja.</linea>	
			<linea>4. Reforzar las esquinas con la cinta.</linea>
			<linea>5. Poner una capa extra de carton en el suelo, o una buena capa de papel de periodico que les encanta!</linea>		
			<linea>6. Extra de tetabriks si se quiere.</linea>		
		</norma>
	</main>
</gato>
